addlib/__init__.py
addlib/addition.py
addlib_test_publish-0.1.0.dist-info/LICENSE
addlib_test_publish-0.1.0.dist-info/METADATA
addlib_test_publish-0.1.0.dist-info/WHEEL
addlib_test_publish-0.1.0.dist-info/RECORD
